oxalis/__init__.py
oxalis/amqp.py
oxalis/base.py
oxalis/beater.py
oxalis/kafka.py
oxalis/pool.py
oxalis/redis.py
oxalis-0.6.6.dist-info/LICENSE
oxalis-0.6.6.dist-info/METADATA
oxalis-0.6.6.dist-info/WHEEL
oxalis-0.6.6.dist-info/RECORD
