Metadata-Version: 2.1
Name: oxalis
Version: 0.6.6
Summary: Distributed async task/job queue
License: MIT
Author: strongbugman
Author-email: strongbugman@gmail.com
Requires-Python: >=3.10,<4.0
Classifier: Environment :: Console
Classifier: License :: OSI Approved :: MIT License
Classifier: Programming Language :: Python :: 3
Classifier: Programming Language :: Python :: 3.10
Classifier: Programming Language :: Python :: 3.11
Classifier: Topic :: Software Development :: Libraries :: Application Frameworks
Classifier: Topic :: Software Development :: Libraries :: Python Modules
Requires-Dist: aio-pika (>=8.0.3)
Requires-Dist: aiokafka (>=0.8.0)
Requires-Dist: croniter (>=1.3.5)
Requires-Dist: redis (>=4.5.1)
